README.md
setup.py
selenium_functions/__init__.py
selenium_functions/selenium_leo.py
selenium_leo.egg-info/PKG-INFO
selenium_leo.egg-info/SOURCES.txt
selenium_leo.egg-info/dependency_links.txt
selenium_leo.egg-info/top_level.txt