Metadata-Version: 2.1
Name: selenium-leo
Version: 1.0
Summary: Funciones utiles de selenium para uso personal
Home-page: https://github.com/silverxd20/selenium_functions
Author: Leo
Author-email: amazongalindo@gmail.com
